flamethrower/agents/drivers/debugging_driver.py
flamethrower/agents/drivers/done_driver.py
flamethrower/agents/drivers/driver_interface.py
flamethrower/agents/drivers/feature_driver.py
flamethrower/agents/drivers/general_driver.py
flamethrower/agents/drivers/tests/test_debugging_driver.py
flamethrower/agents/drivers/tests/test_feature_driver.py
flamethrower/agents/drivers/tests/test_general_driver.py
flamethrower/agents/interpreter.py
flamethrower/agents/operator.py
flamethrower/agents/router.py
flamethrower/agents/util_agents/file_chooser.py
flamethrower/agents/util_agents/file_writer.py
flamethrower/agents/util_agents/summarizer.py
flamethrower/agents/util_agents/tests/test_file_chooser.py
flamethrower/agents/util_agents/tests/test_file_writer.py
flamethrower/config/constants.py
flamethrower/containers/container.py
flamethrower/containers/lm_container.py
flamethrower/containers/tests/test_container.py
flamethrower/containers/tests/test_lm_container.py
flamethrower/context/conv_manager.py
flamethrower/context/prompt.py
flamethrower/context/tests/test_conv_manager.py
flamethrower/context/tests/test_prompt_generator.py
flamethrower/data/.sample.gitignore
flamethrower/data/.sample.zshrc
flamethrower/data/README.md
flamethrower/data/__init__.py
flamethrower/exceptions/exceptions.py
flamethrower/exceptions/handlers.py
flamethrower/models/client_interface.py
flamethrower/models/llm.py
flamethrower/models/models.py
flamethrower/models/openai_client.py
flamethrower/models/tests/test_llm.py
flamethrower/models/tests/test_openai_client.py
flamethrower/py.typed
flamethrower/setup/dir_walker.py
flamethrower/setup/setup.py
flamethrower/setup/summary_manager.py
flamethrower/setup/tests/test_dir_walker.py
flamethrower/setup/tests/test_setup.py
flamethrower/setup/tests/test_summary_manager.py
flamethrower/shell/README.md
flamethrower/shell/__init__.py
flamethrower/shell/command_handler.py
flamethrower/shell/printer.py
flamethrower/shell/shell.py
flamethrower-0.2.32.dist-info/LICENSE
flamethrower-0.2.32.dist-info/METADATA
flamethrower-0.2.32.dist-info/WHEEL
flamethrower-0.2.32.dist-info/entry_points.txt
flamethrower-0.2.32.dist-info/RECORD
