Metadata-Version: 2.1
Name: flamethrower
Version: 0.2.32
Summary: The ultimate debugging experience 🦠🔥
License: MIT
Author: Scott Susanto
Author-email: scottsus@usc.edu
Requires-Python: >=3.08,<4.0
Classifier: License :: OSI Approved :: MIT License
Classifier: Programming Language :: Python :: 3
Classifier: Programming Language :: Python :: 3.8
Classifier: Programming Language :: Python :: 3.9
Classifier: Programming Language :: Python :: 3.10
Classifier: Programming Language :: Python :: 3.11
Classifier: Programming Language :: Python :: 3.12
Requires-Dist: backoff (>=2.2.1,<3.0.0)
Requires-Dist: dependency-injector (>=4.41.0,<5.0.0)
Requires-Dist: gitpython (>=3.1.40,<4.0.0)
Requires-Dist: importlib-resources (>=6.1.1,<7.0.0)
Requires-Dist: jsonschema (>=4.20.0,<5.0.0)
Requires-Dist: openai (>=1.6.1,<2.0.0)
Requires-Dist: pathspec (>=0.12.1,<0.13.0)
Requires-Dist: pydantic (>=2.5.3,<3.0.0)
Requires-Dist: questionary (>=2.0.1,<3.0.0)
Requires-Dist: rich (>=13.7.0,<14.0.0)
Requires-Dist: tiktoken (>=0.5.2,<0.6.0)
Requires-Dist: types-jsonschema (>=4.21.0.20240118,<5.0.0.0)
